{
 "actions": [],
 "creation": "2022-11-22 12:27:26.494931",
 "doctype": "DocType",
 "editable_grid": 1,
 "engine": "InnoDB",
 "field_order": [
  "past_company_name",
  "designation",
  "kra",
  "technologies_used"
 ],
 "fields": [
  {
   "fieldname": "past_company_name",
   "fieldtype": "Data",
   "in_list_view": 1,
   "label": "Past Company Name"
  },
  {
   "fieldname": "designation",
   "fieldtype": "Data",
   "in_list_view": 1,
   "label": "Designation"
  },
  {
   "fieldname": "kra",
   "fieldtype": "Data",
   "in_list_view": 1,
   "label": "KRA"
  },
  {
   "fieldname": "technologies_used",
   "fieldtype": "Data",
   "in_list_view": 1,
   "label": "Technologies Used"
  }
 ],
 "index_web_pages_for_search": 1,
 "istable": 1,
 "links": [],
 "modified": "2022-11-22 12:27:26.494931",
 "modified_by": "Administrator",
 "module": "FrappeReview",
 "name": "EmployeePastCompany",
 "owner": "Administrator",
 "permissions": [],
 "sort_field": "modified",
 "sort_order": "DESC",
 "track_changes": 1
}